Workbook

Sheet Summary
A1: HaqqAI project budget
A2: ="Funding requested: "&TEXT(Assumptions!B4,"#,##0")&" naira over "&Assumptions!B5&" months" -> Funding requested: 50,000,000 naira over 12 months
A4: Category | B4: Amount (₦) | C4: Share of total
A5: Product build out | B5: =SUMIF('Line Items'!$B$2:$B$24,A5,'Line Items'!$H$2:$H$24) -> 20000000 | C5: =B5/$B$11 -> 0.4
A6: Team | B6: =SUMIF('Line Items'!$B$2:$B$24,A6,'Line Items'!$H$2:$H$24) -> 8000000 | C6: =B6/$B$11 -> 0.16
A7: Pilot deployment | B7: =SUMIF('Line Items'!$B$2:$B$24,A7,'Line Items'!$H$2:$H$24) -> 8000000 | C7: =B7/$B$11 -> 0.16
A8: Security, compliance and scale testing | B8: =SUMIF('Line Items'!$B$2:$B$24,A8,'Line Items'!$H$2:$H$24) -> 7000000 | C8: =B8/$B$11 -> 0.14
A9: Infrastructure and operating costs | B9: =SUMIF('Line Items'!$B$2:$B$24,A9,'Line Items'!$H$2:$H$24) -> 5000000 | C9: =B9/$B$11 -> 0.1
A10: Contingency | B10: =SUMIF('Line Items'!$B$2:$B$24,A10,'Line Items'!$H$2:$H$24) -> 2000000 | C10: =B10/$B$11 -> 0.04
A11: Total | B11: =SUM(B5:B10) -> 50000000 | C11: =SUM(C5:C10) -> 1
A14: Detail is on the Line Items sheet. Spending by month is on the Monthly Plan sheet.

Sheet Assumptions
A1: Assumptions and notes
A2: Blue cells are inputs and can be changed. Black cells are formulas.
A4: Funding requested (naira) | B4: 50000000
A5: Project length (months) | B5: 12
A8: Notes
A9: 1. All amounts are planning estimates in naira.
A10: 2. Amounts are treated as including any taxes that apply.
A11: 4. The founder's own pay is not paid from this budget.
A12: 5. Product build out covers contracted design and development work. The part time engineer and the sales support sit under Team.
A13: 6. Recurring costs are spread evenly over their start and end months on the Monthly Plan sheet. One time costs are spread over their stated window.
A14: 7. The contingency reserve is shown in the final month. It is spent only if other costs rise.
A15: 8. Quantity times unit cost gives each line's total on the Line Items sheet. Change a quantity or unit cost there and every other sheet updates.

Sheet Line Items
A1: Ref | B1: Category | C1: Item | D1: Basis | E1: Qty | F1: Unit | G1: Unit cost (₦) | H1: Total (₦) | I1: Start month | J1: End month
A2: P1 | B2: Product build out | C2: Customer assistant interface | D2: Fixed price project, contracted designer and front end developer. Includes setting the assistant up for the six customer uses and showing the confidence score | E2: 1 | F2: project | G2: 6000000 | H2: =E2*G2 -> 6000000 | I2: 1 | J2: 4
A3: P2 | B3: Product build out | C3: Staff knowledge assistant interface | D3: Fixed price project, built on the same verification engine. Includes the HR, IT, operations, customer service and training uses, and the credit, compliance and regulatory assistants | E3: 1 | F3: project | G3: 5000000 | H3: =E3*G3 -> 5000000 | I3: 3 | J3: 6
A4: P3 | B4: Product build out | C4: Verification trace and audit screens | D4: Screens that show each check and its source page to a reviewer | E4: 1 | F4: project | G4: 2500000 | H4: =E4*G4 -> 2500000 | I4: 5 | J4: 7
A5: P4 | B5: Product build out | C5: Retrieval speed and reliability work | D5: Use stored vectors instead of re-embedding, and make repeat runs give consistent answers | E5: 1 | F5: project | G5: 2000000 | H5: =E5*G5 -> 2000000 | I5: 1 | J5: 3
A6: P5 | B6: Product build out | C6: Filing ingestion and company registry tooling | D6: Lets a new institution's documents be added without engineering help | E6: 1 | F6: project | G6: 2500000 | H6: =E6*G6 -> 2500000 | I6: 2 | J6: 4
A7: P6 | B7: Product build out | C7: UI and UX design, user testing with staff | D7: Design work and two rounds of testing with bank staff | E7: 1 | F7: project | G7: 2000000 | H7: =E7*G7 -> 2000000 | I7: 1 | J7: 3
A8: T1 | B8: Team | C8: Part time software engineer | D8: About 20 hours a week for 10 months. Includes building human escalation and the AML/KYC, risk and fraud assistants in months 9 and 10 | E8: 10 | F8: month | G8: 450000 | H8: =E8*G8 -> 4500000 | I8: 2 | J8: 11
A9: T2 | B9: Team | C9: Sales and partnerships support | D9: Monthly retainer for introductions into banks and fintechs | E9: 9 | F9: month | G9: 300000 | H9: =E9*G9 -> 2700000 | I9: 4 | J9: 12
A10: T3 | B10: Team | C10: Banking compliance advisor | D10: Quarterly retainer | E10: 4 | F10: quarter | G10: 200000 | H10: =E10*G10 -> 800000 | I10: 3 | J10: 12
A11: L1 | B11: Pilot deployment | C11: Integration work for one institution | D11: Connecting to a test environment of the pilot bank's own systems | E11: 1 | F11: project | G11: 4000000 | H11: =E11*G11 -> 4000000 | I11: 6 | J11: 8
A12: L2 | B12: Pilot deployment | C12: Deployment and staff training | D12: Set up at the pilot institution and train its users | E12: 1 | F12: project | G12: 1500000 | H12: =E12*G12 -> 1500000 | I12: 8 | J12: 9
A13: L3 | B13: Pilot deployment | C13: Pilot support and monitoring | D13: Three months of support after go live | E13: 3 | F13: month | G13: 500000 | H13: =E13*G13 -> 1500000 | I13: 9 | J13: 11
... A24: C1 | B24: Contingency | C24: Contingency reserve | D24: 4% of the total, kept back for cost changes and used only if needed | E24: 1 | F24: reserve | G24: 2000000 | H24: =E24*G24 -> 2000000 | I24: 12 | J24: 12
C25: Total | H25: =SUM(H2:H24) -> 50000000

Sheet Monthly Plan
A1: Spending by month (₦)
A3: Ref | B3: Item | C3: 1 | D3: 2 | E3: 3 | F3: 4 | G3: 5 | H3: 6 | I3: 7 | J3: 8 | K3: 9 | L3: 10 | M3: 11 | N3: 12 | O3: Total
A4: ='Line Items'!A2 -> P1 | B4: ='Line Items'!C2 -> Customer assistant interface | C4: =IF(AND(C$3>='Line Items'!$I2,C$3<='Line Items'!$J2),'Line Items'!$H2/('Line Items'!$J2-'Line Items'!$I2+1),0) -> 1500000 | D4: =IF(AND(D$3>='Line Items'!$I2,D$3<='Line Items'!$J2),'Line Items'!$H2/('Line Items'!$J2-'Line Items'!$I2+1),0) -> 1500000 | E4: =IF(AND(E$3>='Line Items'!$I2,E$3<='Line Items'!$J2),'Line Items'!$H2/('Line Items'!$J2-'Line Items'!$I2+1),0) -> 1500000 | F4: =IF(AND(F$3>='Line Items'!$I2,F$3<='Line Items'!$J2),'Line Items'!$H2/('Line Items'!$J2-'Line Items'!$I2+1),0) -> 1500000 | G4: =IF(AND(G$3>='Line Items'!$I2,G$3<='Line Items'!$J2),'Line Items'!$H2/('Line Items'!$J2-'Line Items'!$I2+1),0) -> 0 | H4: =IF(AND(H$3>='Line Items'!$I2,H$3<='Line Items'!$J2),'Line Items'!$H2/('Line Items'!$J2-'Line Items'!$I2+1),0) -> 0 | I4: =IF(AND(I$3>='Line Items'!$I2,I$3<='Line Items'!$J2),'Line Items'!$H2/('Line Items'!$J2-'Line Items'!$I2+1),0) -> 0 | J4: =IF(AND(J$3>='Line Items'!$I2,J$3<='Line Items'!$J2),'Line Items'!$H2/('Line Items'!$J2-'Line Items'!$I2+1),0) -> 0 | ... N4: =IF(AND(N$3>='Line Items'!$I2,N$3<='Line Items'!$J2),'Line Items'!$H2/('Line Items'!$J2-'Line Items'!$I2+1),0) -> 0 | O4: =SUM(C4:N4) -> 6000000
A5: ='Line Items'!A3 -> P2 | B5: ='Line Items'!C3 -> Staff knowledge assistant interface | C5: =IF(AND(C$3>='Line Items'!$I3,C$3<='Line Items'!$J3),'Line Items'!$H3/('Line Items'!$J3-'Line Items'!$I3+1),0) -> 0 | D5: =IF(AND(D$3>='Line Items'!$I3,D$3<='Line Items'!$J3),'Line Items'!$H3/('Line Items'!$J3-'Line Items'!$I3+1),0) -> 0 | E5: =IF(AND(E$3>='Line Items'!$I3,E$3<='Line Items'!$J3),'Line Items'!$H3/('Line Items'!$J3-'Line Items'!$I3+1),0) -> 1250000 | F5: =IF(AND(F$3>='Line Items'!$I3,F$3<='Line Items'!$J3),'Line Items'!$H3/('Line Items'!$J3-'Line Items'!$I3+1),0) -> 1250000 | G5: =IF(AND(G$3>='Line Items'!$I3,G$3<='Line Items'!$J3),'Line Items'!$H3/('Line Items'!$J3-'Line Items'!$I3+1),0) -> 1250000 | H5: =IF(AND(H$3>='Line Items'!$I3,H$3<='Line Items'!$J3),'Line Items'!$H3/('Line Items'!$J3-'Line Items'!$I3+1),0) -> 1250000 | I5: =IF(AND(I$3>='Line Items'!$I3,I$3<='Line Items'!$J3),'Line Items'!$H3/('Line Items'!$J3-'Line Items'!$I3+1),0) -> 0 | J5: =IF(AND(J$3>='Line Items'!$I3,J$3<='Line Items'!$J3),'Line Items'!$H3/('Line Items'!$J3-'Line Items'!$I3+1),0) -> 0 | ... N5: =IF(AND(N$3>='Line Items'!$I3,N$3<='Line Items'!$J3),'Line Items'!$H3/('Line Items'!$J3-'Line Items'!$I3+1),0) -> 0 | O5: =SUM(C5:N5) -> 5000000
A6: ='Line Items'!A4 -> P3 | B6: ='Line Items'!C4 -> Verification trace and audit screens | C6: =IF(AND(C$3>='Line Items'!$I4,C$3<='Line Items'!$J4),'Line Items'!$H4/('Line Items'!$J4-'Line Items'!$I4+1),0) -> 0 | D6: =IF(AND(D$3>='Line Items'!$I4,D$3<='Line Items'!$J4),'Line Items'!$H4/('Line Items'!$J4-'Line Items'!$I4+1),0) -> 0 | E6: =IF(AND(E$3>='Line Items'!$I4,E$3<='Line Items'!$J4),'Line Items'!$H4/('Line Items'!$J4-'Line Items'!$I4+1),0) -> 0 | F6: =IF(AND(F$3>='Line Items'!$I4,F$3<='Line Items'!$J4),'Line Items'!$H4/('Line Items'!$J4-'Line Items'!$I4+1),0) -> 0 | G6: =IF(AND(G$3>='Line Items'!$I4,G$3<='Line Items'!$J4),'Line Items'!$H4/('Line Items'!$J4-'Line Items'!$I4+1),0) -> 833333.33 | H6: =IF(AND(H$3>='Line Items'!$I4,H$3<='Line Items'!$J4),'Line Items'!$H4/('Line Items'!$J4-'Line Items'!$I4+1),0) -> 833333.33 | I6: =IF(AND(I$3>='Line Items'!$I4,I$3<='Line Items'!$J4),'Line Items'!$H4/('Line Items'!$J4-'Line Items'!$I4+1),0) -> 833333.33 | J6: =IF(AND(J$3>='Line Items'!$I4,J$3<='Line Items'!$J4),'Line Items'!$H4/('Line Items'!$J4-'Line Items'!$I4+1),0) -> 0 | ... N6: =IF(AND(N$3>='Line Items'!$I4,N$3<='Line Items'!$J4),'Line Items'!$H4/('Line Items'!$J4-'Line Items'!$I4+1),0) -> 0 | O6: =SUM(C6:N6) -> 2500000
A7: ='Line Items'!A5 -> P4 | B7: ='Line Items'!C5 -> Retrieval speed and reliability work | C7: =IF(AND(C$3>='Line Items'!$I5,C$3<='Line Items'!$J5),'Line Items'!$H5/('Line Items'!$J5-'Line Items'!$I5+1),0) -> 666666.67 | D7: =IF(AND(D$3>='Line Items'!$I5,D$3<='Line Items'!$J5),'Line Items'!$H5/('Line Items'!$J5-'Line Items'!$I5+1),0) -> 666666.67 | E7: =IF(AND(E$3>='Line Items'!$I5,E$3<='Line Items'!$J5),'Line Items'!$H5/('Line Items'!$J5-'Line Items'!$I5+1),0) -> 666666.67 | F7: =IF(AND(F$3>='Line Items'!$I5,F$3<='Line Items'!$J5),'Line Items'!$H5/('Line Items'!$J5-'Line Items'!$I5+1),0) -> 0 | G7: =IF(AND(G$3>='Line Items'!$I5,G$3<='Line Items'!$J5),'Line Items'!$H5/('Line Items'!$J5-'Line Items'!$I5+1),0) -> 0 | H7: =IF(AND(H$3>='Line Items'!$I5,H$3<='Line Items'!$J5),'Line Items'!$H5/('Line Items'!$J5-'Line Items'!$I5+1),0) -> 0 | I7: =IF(AND(I$3>='Line Items'!$I5,I$3<='Line Items'!$J5),'Line Items'!$H5/('Line Items'!$J5-'Line Items'!$I5+1),0) -> 0 | J7: =IF(AND(J$3>='Line Items'!$I5,J$3<='Line Items'!$J5),'Line Items'!$H5/('Line Items'!$J5-'Line Items'!$I5+1),0) -> 0 | ... N7: =IF(AND(N$3>='Line Items'!$I5,N$3<='Line Items'!$J5),'Line Items'!$H5/('Line Items'!$J5-'Line Items'!$I5+1),0) -> 0 | O7: =SUM(C7:N7) -> 2000000
A8: ='Line Items'!A6 -> P5 | B8: ='Line Items'!C6 -> Filing ingestion and company registry tooling | C8: =IF(AND(C$3>='Line Items'!$I6,C$3<='Line Items'!$J6),'Line Items'!$H6/('Line Items'!$J6-'Line Items'!$I6+1),0) -> 0 | D8: =IF(AND(D$3>='Line Items'!$I6,D$3<='Line Items'!$J6),'Line Items'!$H6/('Line Items'!$J6-'Line Items'!$I6+1),0) -> 833333.33 | E8: =IF(AND(E$3>='Line Items'!$I6,E$3<='Line Items'!$J6),'Line Items'!$H6/('Line Items'!$J6-'Line Items'!$I6+1),0) -> 833333.33 | F8: =IF(AND(F$3>='Line Items'!$I6,F$3<='Line Items'!$J6),'Line Items'!$H6/('Line Items'!$J6-'Line Items'!$I6+1),0) -> 833333.33 | G8: =IF(AND(G$3>='Line Items'!$I6,G$3<='Line Items'!$J6),'Line Items'!$H6/('Line Items'!$J6-'Line Items'!$I6+1),0) -> 0 | H8: =IF(AND(H$3>='Line Items'!$I6,H$3<='Line Items'!$J6),'Line Items'!$H6/('Line Items'!$J6-'Line Items'!$I6+1),0) -> 0 | I8: =IF(AND(I$3>='Line Items'!$I6,I$3<='Line Items'!$J6),'Line Items'!$H6/('Line Items'!$J6-'Line Items'!$I6+1),0) -> 0 | J8: =IF(AND(J$3>='Line Items'!$I6,J$3<='Line Items'!$J6),'Line Items'!$H6/('Line Items'!$J6-'Line Items'!$I6+1),0) -> 0 | ... N8: =IF(AND(N$3>='Line Items'!$I6,N$3<='Line Items'!$J6),'Line Items'!$H6/('Line Items'!$J6-'Line Items'!$I6+1),0) -> 0 | O8: =SUM(C8:N8) -> 2500000
A9: ='Line Items'!A7 -> P6 | B9: ='Line Items'!C7 -> UI and UX design, user testing with staff | C9: =IF(AND(C$3>='Line Items'!$I7,C$3<='Line Items'!$J7),'Line Items'!$H7/('Line Items'!$J7-'Line Items'!$I7+1),0) -> 666666.67 | D9: =IF(AND(D$3>='Line Items'!$I7,D$3<='Line Items'!$J7),'Line Items'!$H7/('Line Items'!$J7-'Line Items'!$I7+1),0) -> 666666.67 | E9: =IF(AND(E$3>='Line Items'!$I7,E$3<='Line Items'!$J7),'Line Items'!$H7/('Line Items'!$J7-'Line Items'!$I7+1),0) -> 666666.67 | F9: =IF(AND(F$3>='Line Items'!$I7,F$3<='Line Items'!$J7),'Line Items'!$H7/('Line Items'!$J7-'Line Items'!$I7+1),0) -> 0 | G9: =IF(AND(G$3>='Line Items'!$I7,G$3<='Line Items'!$J7),'Line Items'!$H7/('Line Items'!$J7-'Line Items'!$I7+1),0) -> 0 | H9: =IF(AND(H$3>='Line Items'!$I7,H$3<='Line Items'!$J7),'Line Items'!$H7/('Line Items'!$J7-'Line Items'!$I7+1),0) -> 0 | I9: =IF(AND(I$3>='Line Items'!$I7,I$3<='Line Items'!$J7),'Line Items'!$H7/('Line Items'!$J7-'Line Items'!$I7+1),0) -> 0 | J9: =IF(AND(J$3>='Line Items'!$I7,J$3<='Line Items'!$J7),'Line Items'!$H7/('Line Items'!$J7-'Line Items'!$I7+1),0) -> 0 | ... N9: =IF(AND(N$3>='Line Items'!$I7,N$3<='Line Items'!$J7),'Line Items'!$H7/('Line Items'!$J7-'Line Items'!$I7+1),0) -> 0 | O9: =SUM(C9:N9) -> 2000000
A10: ='Line Items'!A8 -> T1 | B10: ='Line Items'!C8 -> Part time software engineer | C10: =IF(AND(C$3>='Line Items'!$I8,C$3<='Line Items'!$J8),'Line Items'!$H8/('Line Items'!$J8-'Line Items'!$I8+1),0) -> 0 | D10: =IF(AND(D$3>='Line Items'!$I8,D$3<='Line Items'!$J8),'Line Items'!$H8/('Line Items'!$J8-'Line Items'!$I8+1),0) -> 450000 | E10: =IF(AND(E$3>='Line Items'!$I8,E$3<='Line Items'!$J8),'Line Items'!$H8/('Line Items'!$J8-'Line Items'!$I8+1),0) -> 450000 | F10: =IF(AND(F$3>='Line Items'!$I8,F$3<='Line Items'!$J8),'Line Items'!$H8/('Line Items'!$J8-'Line Items'!$I8+1),0) -> 450000 | G10: =IF(AND(G$3>='Line Items'!$I8,G$3<='Line Items'!$J8),'Line Items'!$H8/('Line Items'!$J8-'Line Items'!$I8+1),0) -> 450000 | H10: =IF(AND(H$3>='Line Items'!$I8,H$3<='Line Items'!$J8),'Line Items'!$H8/('Line Items'!$J8-'Line Items'!$I8+1),0) -> 450000 | I10: =IF(AND(I$3>='Line Items'!$I8,I$3<='Line Items'!$J8),'Line Items'!$H8/('Line Items'!$J8-'Line Items'!$I8+1),0) -> 450000 | J10: =IF(AND(J$3>='Line Items'!$I8,J$3<='Line Items'!$J8),'Line Items'!$H8/('Line Items'!$J8-'Line Items'!$I8+1),0) -> 450000 | ... N10: =IF(AND(N$3>='Line Items'!$I8,N$3<='Line Items'!$J8),'Line Items'!$H8/('Line Items'!$J8-'Line Items'!$I8+1),0) -> 0 | O10: =SUM(C10:N10) -> 4500000
A11: ='Line Items'!A9 -> T2 | B11: ='Line Items'!C9 -> Sales and partnerships support | C11: =IF(AND(C$3>='Line Items'!$I9,C$3<='Line Items'!$J9),'Line Items'!$H9/('Line Items'!$J9-'Line Items'!$I9+1),0) -> 0 | D11: =IF(AND(D$3>='Line Items'!$I9,D$3<='Line Items'!$J9),'Line Items'!$H9/('Line Items'!$J9-'Line Items'!$I9+1),0) -> 0 | E11: =IF(AND(E$3>='Line Items'!$I9,E$3<='Line Items'!$J9),'Line Items'!$H9/('Line Items'!$J9-'Line Items'!$I9+1),0) -> 0 | F11: =IF(AND(F$3>='Line Items'!$I9,F$3<='Line Items'!$J9),'Line Items'!$H9/('Line Items'!$J9-'Line Items'!$I9+1),0) -> 300000 | G11: =IF(AND(G$3>='Line Items'!$I9,G$3<='Line Items'!$J9),'Line Items'!$H9/('Line Items'!$J9-'Line Items'!$I9+1),0) -> 300000 | H11: =IF(AND(H$3>='Line Items'!$I9,H$3<='Line Items'!$J9),'Line Items'!$H9/('Line Items'!$J9-'Line Items'!$I9+1),0) -> 300000 | I11: =IF(AND(I$3>='Line Items'!$I9,I$3<='Line Items'!$J9),'Line Items'!$H9/('Line Items'!$J9-'Line Items'!$I9+1),0) -> 300000 | J11: =IF(AND(J$3>='Line Items'!$I9,J$3<='Line Items'!$J9),'Line Items'!$H9/('Line Items'!$J9-'Line Items'!$I9+1),0) -> 300000 | ... N11: =IF(AND(N$3>='Line Items'!$I9,N$3<='Line Items'!$J9),'Line Items'!$H9/('Line Items'!$J9-'Line Items'!$I9+1),0) -> 300000 | O11: =SUM(C11:N11) -> 2700000
A12: ='Line Items'!A10 -> T3 | B12: ='Line Items'!C10 -> Banking compliance advisor | C12: =IF(AND(C$3>='Line Items'!$I10,C$3<='Line Items'!$J10),'Line Items'!$H10/('Line Items'!$J10-'Line Items'!$I10+1),0) -> 0 | D12: =IF(AND(D$3>='Line Items'!$I10,D$3<='Line Items'!$J10),'Line Items'!$H10/('Line Items'!$J10-'Line Items'!$I10+1),0) -> 0 | E12: =IF(AND(E$3>='Line Items'!$I10,E$3<='Line Items'!$J10),'Line Items'!$H10/('Line Items'!$J10-'Line Items'!$I10+1),0) -> 80000 | F12: =IF(AND(F$3>='Line Items'!$I10,F$3<='Line Items'!$J10),'Line Items'!$H10/('Line Items'!$J10-'Line Items'!$I10+1),0) -> 80000 | G12: =IF(AND(G$3>='Line Items'!$I10,G$3<='Line Items'!$J10),'Line Items'!$H10/('Line Items'!$J10-'Line Items'!$I10+1),0) -> 80000 | H12: =IF(AND(H$3>='Line Items'!$I10,H$3<='Line Items'!$J10),'Line Items'!$H10/('Line Items'!$J10-'Line Items'!$I10+1),0) -> 80000 | I12: =IF(AND(I$3>='Line Items'!$I10,I$3<='Line Items'!$J10),'Line Items'!$H10/('Line Items'!$J10-'Line Items'!$I10+1),0) -> 80000 | J12: =IF(AND(J$3>='Line Items'!$I10,J$3<='Line Items'!$J10),'Line Items'!$H10/('Line Items'!$J10-'Line Items'!$I10+1),0) -> 80000 | ... N12: =IF(AND(N$3>='Line Items'!$I10,N$3<='Line Items'!$J10),'Line Items'!$H10/('Line Items'!$J10-'Line Items'!$I10+1),0) -> 80000 | O12: =SUM(C12:N12) -> 800000
A13: ='Line Items'!A11 -> L1 | B13: ='Line Items'!C11 -> Integration work for one institution | C13: =IF(AND(C$3>='Line Items'!$I11,C$3<='Line Items'!$J11),'Line Items'!$H11/('Line Items'!$J11-'Line Items'!$I11+1),0) -> 0 | D13: =IF(AND(D$3>='Line Items'!$I11,D$3<='Line Items'!$J11),'Line Items'!$H11/('Line Items'!$J11-'Line Items'!$I11+1),0) -> 0 | E13: =IF(AND(E$3>='Line Items'!$I11,E$3<='Line Items'!$J11),'Line Items'!$H11/('Line Items'!$J11-'Line Items'!$I11+1),0) -> 0 | F13: =IF(AND(F$3>='Line Items'!$I11,F$3<='Line Items'!$J11),'Line Items'!$H11/('Line Items'!$J11-'Line Items'!$I11+1),0) -> 0 | G13: =IF(AND(G$3>='Line Items'!$I11,G$3<='Line Items'!$J11),'Line Items'!$H11/('Line Items'!$J11-'Line Items'!$I11+1),0) -> 0 | H13: =IF(AND(H$3>='Line Items'!$I11,H$3<='Line Items'!$J11),'Line Items'!$H11/('Line Items'!$J11-'Line Items'!$I11+1),0) -> 1333333.3 | I13: =IF(AND(I$3>='Line Items'!$I11,I$3<='Line Items'!$J11),'Line Items'!$H11/('Line Items'!$J11-'Line Items'!$I11+1),0) -> 1333333.3 | J13: =IF(AND(J$3>='Line Items'!$I11,J$3<='Line Items'!$J11),'Line Items'!$H11/('Line Items'!$J11-'Line Items'!$I11+1),0) -> 1333333.3 | ... N13: =IF(AND(N$3>='Line Items'!$I11,N$3<='Line Items'!$J11),'Line Items'!$H11/('Line Items'!$J11-'Line Items'!$I11+1),0) -> 0 | O13: =SUM(C13:N13) -> 4000000
A14: ='Line Items'!A12 -> L2 | B14: ='Line Items'!C12 -> Deployment and staff training | C14: =IF(AND(C$3>='Line Items'!$I12,C$3<='Line Items'!$J12),'Line Items'!$H12/('Line Items'!$J12-'Line Items'!$I12+1),0) -> 0 | D14: =IF(AND(D$3>='Line Items'!$I12,D$3<='Line Items'!$J12),'Line Items'!$H12/('Line Items'!$J12-'Line Items'!$I12+1),0) -> 0 | E14: =IF(AND(E$3>='Line Items'!$I12,E$3<='Line Items'!$J12),'Line Items'!$H12/('Line Items'!$J12-'Line Items'!$I12+1),0) -> 0 | F14: =IF(AND(F$3>='Line Items'!$I12,F$3<='Line Items'!$J12),'Line Items'!$H12/('Line Items'!$J12-'Line Items'!$I12+1),0) -> 0 | G14: =IF(AND(G$3>='Line Items'!$I12,G$3<='Line Items'!$J12),'Line Items'!$H12/('Line Items'!$J12-'Line Items'!$I12+1),0) -> 0 | H14: =IF(AND(H$3>='Line Items'!$I12,H$3<='Line Items'!$J12),'Line Items'!$H12/('Line Items'!$J12-'Line Items'!$I12+1),0) -> 0 | I14: =IF(AND(I$3>='Line Items'!$I12,I$3<='Line Items'!$J12),'Line Items'!$H12/('Line Items'!$J12-'Line Items'!$I12+1),0) -> 0 | J14: =IF(AND(J$3>='Line Items'!$I12,J$3<='Line Items'!$J12),'Line Items'!$H12/('Line Items'!$J12-'Line Items'!$I12+1),0) -> 750000 | ... N14: =IF(AND(N$3>='Line Items'!$I12,N$3<='Line Items'!$J12),'Line Items'!$H12/('Line Items'!$J12-'Line Items'!$I12+1),0) -> 0 | O14: =SUM(C14:N14) -> 1500000
A15: ='Line Items'!A13 -> L3 | B15: ='Line Items'!C13 -> Pilot support and monitoring | C15: =IF(AND(C$3>='Line Items'!$I13,C$3<='Line Items'!$J13),'Line Items'!$H13/('Line Items'!$J13-'Line Items'!$I13+1),0) -> 0 | D15: =IF(AND(D$3>='Line Items'!$I13,D$3<='Line Items'!$J13),'Line Items'!$H13/('Line Items'!$J13-'Line Items'!$I13+1),0) -> 0 | E15: =IF(AND(E$3>='Line Items'!$I13,E$3<='Line Items'!$J13),'Line Items'!$H13/('Line Items'!$J13-'Line Items'!$I13+1),0) -> 0 | F15: =IF(AND(F$3>='Line Items'!$I13,F$3<='Line Items'!$J13),'Line Items'!$H13/('Line Items'!$J13-'Line Items'!$I13+1),0) -> 0 | G15: =IF(AND(G$3>='Line Items'!$I13,G$3<='Line Items'!$J13),'Line Items'!$H13/('Line Items'!$J13-'Line Items'!$I13+1),0) -> 0 | H15: =IF(AND(H$3>='Line Items'!$I13,H$3<='Line Items'!$J13),'Line Items'!$H13/('Line Items'!$J13-'Line Items'!$I13+1),0) -> 0 | I15: =IF(AND(I$3>='Line Items'!$I13,I$3<='Line Items'!$J13),'Line Items'!$H13/('Line Items'!$J13-'Line Items'!$I13+1),0) -> 0 | J15: =IF(AND(J$3>='Line Items'!$I13,J$3<='Line Items'!$J13),'Line Items'!$H13/('Line Items'!$J13-'Line Items'!$I13+1),0) -> 0 | ... N15: =IF(AND(N$3>='Line Items'!$I13,N$3<='Line Items'!$J13),'Line Items'!$H13/('Line Items'!$J13-'Line Items'!$I13+1),0) -> 0 | O15: =SUM(C15:N15) -> 1500000
... A26: ='Line Items'!A24 -> C1 | B26: ='Line Items'!C24 -> Contingency reserve | C26: =IF(AND(C$3>='Line Items'!$I24,C$3<='Line Items'!$J24),'Line Items'!$H24/('Line Items'!$J24-'Line Items'!$I24+1),0) -> 0 | D26: =IF(AND(D$3>='Line Items'!$I24,D$3<='Line Items'!$J24),'Line Items'!$H24/('Line Items'!$J24-'Line Items'!$I24+1),0) -> 0 | E26: =IF(AND(E$3>='Line Items'!$I24,E$3<='Line Items'!$J24),'Line Items'!$H24/('Line Items'!$J24-'Line Items'!$I24+1),0) -> 0 | F26: =IF(AND(F$3>='Line Items'!$I24,F$3<='Line Items'!$J24),'Line Items'!$H24/('Line Items'!$J24-'Line Items'!$I24+1),0) -> 0 | G26: =IF(AND(G$3>='Line Items'!$I24,G$3<='Line Items'!$J24),'Line Items'!$H24/('Line Items'!$J24-'Line Items'!$I24+1),0) -> 0 | H26: =IF(AND(H$3>='Line Items'!$I24,H$3<='Line Items'!$J24),'Line Items'!$H24/('Line Items'!$J24-'Line Items'!$I24+1),0) -> 0 | I26: =IF(AND(I$3>='Line Items'!$I24,I$3<='Line Items'!$J24),'Line Items'!$H24/('Line Items'!$J24-'Line Items'!$I24+1),0) -> 0 | J26: =IF(AND(J$3>='Line Items'!$I24,J$3<='Line Items'!$J24),'Line Items'!$H24/('Line Items'!$J24-'Line Items'!$I24+1),0) -> 0 | ... N26: =IF(AND(N$3>='Line Items'!$I24,N$3<='Line Items'!$J24),'Line Items'!$H24/('Line Items'!$J24-'Line Items'!$I24+1),0) -> 2000000 | O26: =SUM(C26:N26) -> 2000000
B27: Total for the month | C27: =SUM(C4:C26) -> 3250000 | D27: =SUM(D4:D26) -> 5133333.3 | E27: =SUM(E4:E26) -> 7063333.3 | F27: =SUM(F4:F26) -> 5541111.1 | G27: =SUM(G4:G26) -> 4041111.1 | H27: =SUM(H4:H26) -> 5524444.4 | I27: =SUM(I4:I26) -> 5524444.4 | J27: =SUM(J4:J26) -> 4691111.1 | ... O27: =SUM(O4:O26) -> 50000000
B28: Running total | C28: =C27 -> 3250000 | D28: =C28+D27 -> 8383333.3 | E28: =D28+E27 -> 15446667 | F28: =E28+F27 -> 20987778 | G28: =F28+G27 -> 25028889 | H28: =G28+H27 -> 30553333 | I28: =H28+I27 -> 36077778 | J28: =I28+J27 -> 40768889 | K28: =J28+K27 -> 43376667 | ... N28: =M28+N27 -> 50000000
